app.py
routes.py
server.py
weather.py
mseep_fastapi_mcp_sse-0.1.3.dist-info/licenses/LICENSE
mseep_fastapi_mcp_sse-0.1.3.dist-info/METADATA
mseep_fastapi_mcp_sse-0.1.3.dist-info/WHEEL
mseep_fastapi_mcp_sse-0.1.3.dist-info/entry_points.txt
mseep_fastapi_mcp_sse-0.1.3.dist-info/top_level.txt
mseep_fastapi_mcp_sse-0.1.3.dist-info/RECORD
